uv_burn/__init__.py
uv_burn/convert.py
uv_burn/io.py
uv_burn/main.py
uv_burn/models/__init__.py
uv_burn/models/pipenv.py
uv_burn/models/pipenv_lock.py
uv_burn/models/pyproject.py
uv_burn/models/repository.py
uv_burn/models/uv_lock.py
uv_burn/repository.py
uv_burn-0.1.1.dist-info/WHEEL
uv_burn-0.1.1.dist-info/entry_points.txt
uv_burn-0.1.1.dist-info/METADATA
uv_burn-0.1.1.dist-info/RECORD
