Metadata-Version: 2.3
Name: uv-burn
Version: 0.1.1
Summary: Convert uv (Astral) project files (pyproject.toml + uv.lock) into Pipenv (Pipfile + Pipfile.lock) so security tooling like Veracode can scan projects that don't yet support uv directly.
Keywords: uv,pipenv,converter,veracode,security,pyproject,lockfile
License: MIT License
Classifier: Programming Language :: Python :: 3
Classifier: Programming Language :: Python :: 3.12
Classifier: License :: OSI Approved :: MIT License
Classifier: Intended Audience :: Developers
Classifier: Topic :: Software Development :: Build Tools
Classifier: Topic :: Security
Requires-Dist: httpx>=0.28.1
Requires-Dist: packaging>=25.0
Requires-Dist: pydantic>=2.11.7
Requires-Dist: rich>=14.1.0
Requires-Dist: tomli-w>=1.2.0
Requires-Dist: typer>=0.16.1
Requires-Python: >=3.12
